seshat_classifier/__init__.py
seshat_classifier/seshat.py
seshat_classifier/data/veg_zps_spitzer_2mass_jwst.csv
seshat_classifier-0.1.5.dist-info/licenses/LICENSE
seshat_classifier-0.1.5.dist-info/METADATA
seshat_classifier-0.1.5.dist-info/WHEEL
seshat_classifier-0.1.5.dist-info/top_level.txt
seshat_classifier-0.1.5.dist-info/RECORD
