Metadata-Version: 2.4
Name: seshat_classifier
Version: 0.1.5
Summary: A package for classifying tabular photometry data from JWST, Spitzer, and 2MASS according to one of YSOs, field stars, brown dwarfs, white dwarfs, or galaxies.
Author-email: Breanna Crompvoets <bcrompvoets@uvic.ca>
License-Expression: MIT
Classifier: Programming Language :: Python :: 3
Classifier: Operating System :: OS Independent
Requires-Python: >=3.9
License-File: LICENSE
Requires-Dist: numpy>=1.26.4
Requires-Dist: pandas>=2.2.0
Requires-Dist: matplotlib>=3.7.0
Requires-Dist: seaborn>=0.12.0
Requires-Dist: scikit-learn>=1.3.0
Requires-Dist: astropy>=6.0.0
Requires-Dist: xgboost>=1.7.0
Requires-Dist: requests<3.0.0,>=2.31.0
Dynamic: license-file
